health_report/__init__.py
health_report/cli.py
health_report/manage.py
health_report/apis/__init__.py
health_report/apis/admin.py
health_report/apis/apps.py
health_report/apis/models.py
health_report/apis/serializers.py
health_report/apis/tests.py
health_report/apis/urls.py
health_report/apis/views.py
health_report/apis/migrations/__init__.py
health_report/database_report/__init__.py
health_report/database_report/admin.py
health_report/database_report/apps.py
health_report/database_report/models.py
health_report/database_report/tests.py
health_report/database_report/urls.py
health_report/database_report/views.py
health_report/database_report/migrations/0001_initial.py
health_report/database_report/migrations/__init__.py
health_report/health_report/__init__.py
health_report/health_report/asgi.py
health_report/health_report/settings.py
health_report/health_report/urls.py
health_report/health_report/views.py
health_report/health_report/wsgi.py
health_report/login_app/__init__.py
health_report/login_app/admin.py
health_report/login_app/apps.py
health_report/login_app/forms.py
health_report/login_app/models.py
health_report/login_app/tests.py
health_report/login_app/urls.py
health_report/login_app/views.py
health_report/login_app/migrations/0001_initial.py
health_report/login_app/migrations/0002_alter_odoosetup_url.py
health_report/login_app/migrations/__init__.py
health_report/login_app/templates/odoo_setup_form.html
health_report/system_report/__init__.py
health_report/system_report/admin.py
health_report/system_report/apps.py
health_report/system_report/methods.py
health_report/system_report/models.py
health_report/system_report/tests.py
health_report/system_report/urls.py
health_report/system_report/views.py
health_report/system_report/migrations/0001_initial.py
health_report/system_report/migrations/__init__.py
health_report/system_report/templates/report_dashboard.html
odoo_health_report_mar14-0.1.9.dist-info/LICENSE
odoo_health_report_mar14-0.1.9.dist-info/METADATA
odoo_health_report_mar14-0.1.9.dist-info/WHEEL
odoo_health_report_mar14-0.1.9.dist-info/entry_points.txt
odoo_health_report_mar14-0.1.9.dist-info/top_level.txt
odoo_health_report_mar14-0.1.9.dist-info/RECORD
